{"data":[{"files":[{"filename":"/src/hpp-proto/build/_deps/is_utf8-src/src/is_utf8.cpp","summary":{"branches":{"count":108,"covered":18,"notcovered":90,"percent":16.666666666666664},"functions":{"count":342,"covered":32,"percent":9.3567251461988299},"instantiations":{"count":388,"covered":34,"percent":8.7628865979381434},"lines":{"count":1452,"covered":226,"percent":15.564738292011018},"mcdc":{"count":0,"covered":0,"notcovered":0,"percent":0},"regions":{"count":544,"covered":83,"notcovered":461,"percent":15.257352941176471}}},{"filename":"/src/hpp-proto/build/include/google/protobuf/any.desc.hpp","summary":{"branches":{"count":0,"covered":0,"notcovered":0,"percent":0},"functions":{"count":1,"covered":0,"percent":0},"instantiations":{"count":1,"covered":0,"percent":0},"lines":{"count":5,"covered":0,"percent":0},"mcdc":{"count":0,"covered":0,"notcovered":0,"percent":0},"regions":{"count":1,"covered":0,"notcovered":1,"percent":0}}},{"filename":"/src/hpp-proto/build/include/google/protobuf/duration.desc.hpp","summary":{"branches":{"count":0,"covered":0,"notcovered":0,"percent":0},"functions":{"count":1,"covered":0,"percent":0},"instantiations":{"count":1,"covered":0,"percent":0},"lines":{"count":5,"covered":0,"percent":0},"mcdc":{"count":0,"covered":0,"notcovered":0,"percent":0},"regions":{"count":1,"covered":0,"notcovered":1,"percent":0}}},{"filename":"/src/hpp-proto/build/include/google/protobuf/duration.msg.hpp","summary":{"branches":{"count":0,"covered":0,"notcovered":0,"percent":0},"functions":{"count":1,"covered":0,"percent":0},"instantiations":{"count":1,"covered":0,"percent":0},"lines":{"count":1,"covered":0,"percent":0},"mcdc":{"count":0,"covered":0,"notcovered":0,"percent":0},"regions":{"count":1,"covered":0,"notcovered":1,"percent":0}}},{"filename":"/src/hpp-proto/build/include/google/protobuf/field_mask.desc.hpp","summary":{"branches":{"count":0,"covered":0,"notcovered":0,"percent":0},"functions":{"count":1,"covered":0,"percent":0},"instantiations":{"count":1,"covered":0,"percent":0},"lines":{"count":5,"covered":0,"percent":0},"mcdc":{"count":0,"covered":0,"notcovered":0,"percent":0},"regions":{"count":1,"covered":0,"notcovered":1,"percent":0}}},{"filename":"/src/hpp-proto/build/include/google/protobuf/field_mask.msg.hpp","summary":{"branches":{"count":0,"covered":0,"notcovered":0,"percent":0},"functions":{"count":1,"covered":0,"percent":0},"instantiations":{"count":1,"covered":0,"percent":0},"lines":{"count":1,"covered":0,"percent":0},"mcdc":{"count":0,"covered":0,"notcovered":0,"percent":0},"regions":{"count":1,"covered":0,"notcovered":1,"percent":0}}},{"filename":"/src/hpp-proto/build/include/google/protobuf/struct.desc.hpp","summary":{"branches":{"count":0,"covered":0,"notcovered":0,"percent":0},"functions":{"count":1,"covered":0,"percent":0},"instantiations":{"count":1,"covered":0,"percent":0},"lines":{"count":5,"covered":0,"percent":0},"mcdc":{"count":0,"covered":0,"notcovered":0,"percent":0},"regions":{"count":1,"covered":0,"notcovered":1,"percent":0}}},{"filename":"/src/hpp-proto/build/include/google/protobuf/struct.msg.hpp","summary":{"branches":{"count":0,"covered":0,"notcovered":0,"percent":0},"functions":{"count":1,"covered":0,"percent":0},"instantiations":{"count":1,"covered":0,"percent":0},"lines":{"count":4,"covered":0,"percent":0},"mcdc":{"count":0,"covered":0,"notcovered":0,"percent":0},"regions":{"count":1,"covered":0,"notcovered":1,"percent":0}}},{"filename":"/src/hpp-proto/build/include/google/protobuf/timestamp.desc.hpp","summary":{"branches":{"count":0,"covered":0,"notcovered":0,"percent":0},"functions":{"count":1,"covered":0,"percent":0},"instantiations":{"count":1,"covered":0,"percent":0},"lines":{"count":5,"covered":0,"percent":0},"mcdc":{"count":0,"covered":0,"notcovered":0,"percent":0},"regions":{"count":1,"covered":0,"notcovered":1,"percent":0}}},{"filename":"/src/hpp-proto/build/include/google/protobuf/timestamp.msg.hpp","summary":{"branches":{"count":0,"covered":0,"notcovered":0,"percent":0},"functions":{"count":1,"covered":0,"percent":0},"instantiations":{"count":1,"covered":0,"percent":0},"lines":{"count":1,"covered":0,"percent":0},"mcdc":{"count":0,"covered":0,"notcovered":0,"percent":0},"regions":{"count":1,"covered":0,"notcovered":1,"percent":0}}},{"filename":"/src/hpp-proto/build/include/google/protobuf/wrappers.desc.hpp","summary":{"branches":{"count":0,"covered":0,"notcovered":0,"percent":0},"functions":{"count":1,"covered":0,"percent":0},"instantiations":{"count":1,"covered":0,"percent":0},"lines":{"count":5,"covered":0,"percent":0},"mcdc":{"count":0,"covered":0,"notcovered":0,"percent":0},"regions":{"count":1,"covered":0,"notcovered":1,"percent":0}}},{"filename":"/src/hpp-proto/fuzz/common.cpp","summary":{"branches":{"count":10,"covered":5,"notcovered":5,"percent":50},"functions":{"count":2,"covered":2,"percent":100},"instantiations":{"count":2,"covered":2,"percent":100},"lines":{"count":27,"covered":18,"percent":66.666666666666657},"mcdc":{"count":0,"covered":0,"notcovered":0,"percent":0},"regions":{"count":17,"covered":12,"notcovered":5,"percent":70.588235294117652}}},{"filename":"/src/hpp-proto/fuzz/common.hpp","summary":{"branches":{"count":0,"covered":0,"notcovered":0,"percent":0},"functions":{"count":3,"covered":2,"percent":66.666666666666657},"instantiations":{"count":5,"covered":4,"percent":80},"lines":{"count":14,"covered":10,"percent":71.428571428571431},"mcdc":{"count":0,"covered":0,"notcovered":0,"percent":0},"regions":{"count":3,"covered":2,"notcovered":1,"percent":66.666666666666657}}},{"filename":"/src/hpp-proto/fuzz/fuzz_binpb.cpp","summary":{"branches":{"count":36,"covered":17,"notcovered":19,"percent":47.222222222222221},"functions":{"count":5,"covered":5,"percent":100},"instantiations":{"count":17,"covered":17,"percent":100},"lines":{"count":135,"covered":124,"percent":91.851851851851848},"mcdc":{"count":0,"covered":0,"notcovered":0,"percent":0},"regions":{"count":113,"covered":51,"notcovered":62,"percent":45.132743362831853}}},{"filename":"/src/hpp-proto/fuzz/fuzz_json.cpp","summary":{"branches":{"count":24,"covered":11,"notcovered":13,"percent":45.833333333333329},"functions":{"count":5,"covered":4,"percent":80},"instantiations":{"count":15,"covered":12,"percent":80},"lines":{"count":133,"covered":112,"percent":84.210526315789465},"mcdc":{"count":0,"covered":0,"notcovered":0,"percent":0},"regions":{"count":57,"covered":30,"notcovered":27,"percent":52.631578947368418}}},{"filename":"/src/hpp-proto/include/google/protobuf/descriptor.msg.hpp","summary":{"branches":{"count":4,"covered":0,"notcovered":4,"percent":0},"functions":{"count":20,"covered":0,"percent":0},"instantiations":{"count":20,"covered":0,"percent":0},"lines":{"count":82,"covered":0,"percent":0},"mcdc":{"count":0,"covered":0,"notcovered":0,"percent":0},"regions":{"count":22,"covered":0,"notcovered":22,"percent":0}}},{"filename":"/src/hpp-proto/include/hpp_proto/binpb.hpp","summary":{"branches":{"count":2,"covered":1,"notcovered":1,"percent":50},"functions":{"count":3,"covered":1,"percent":33.333333333333329},"instantiations":{"count":3,"covered":1,"percent":33.333333333333329},"lines":{"count":16,"covered":6,"percent":37.5},"mcdc":{"count":0,"covered":0,"notcovered":0,"percent":0},"regions":{"count":6,"covered":3,"notcovered":3,"percent":50}}},{"filename":"/src/hpp-proto/include/hpp_proto/binpb/deserialize.hpp","summary":{"branches":{"count":208,"covered":69,"notcovered":139,"percent":33.17307692307692},"functions":{"count":83,"covered":53,"percent":63.855421686746979},"instantiations":{"count":1891,"covered":421,"percent":22.263352723426756},"lines":{"count":704,"covered":340,"percent":48.295454545454547},"mcdc":{"count":0,"covered":0,"notcovered":0,"percent":0},"regions":{"count":422,"covered":199,"notcovered":223,"percent":47.156398104265399}}},{"filename":"/src/hpp-proto/include/hpp_proto/binpb/meta.hpp","summary":{"branches":{"count":130,"covered":47,"notcovered":83,"percent":36.153846153846153},"functions":{"count":29,"covered":8,"percent":27.586206896551722},"instantiations":{"count":2567,"covered":200,"percent":7.7911959485781068},"lines":{"count":116,"covered":37,"percent":31.896551724137932},"mcdc":{"count":0,"covered":0,"notcovered":0,"percent":0},"regions":{"count":167,"covered":116,"notcovered":51,"percent":69.461077844311376}}},{"filename":"/src/hpp-proto/include/hpp_proto/binpb/serialize.hpp","summary":{"branches":{"count":123,"covered":0,"notcovered":123,"percent":0},"functions":{"count":46,"covered":0,"percent":0},"instantiations":{"count":1633,"covered":0,"percent":0},"lines":{"count":272,"covered":0,"percent":0},"mcdc":{"count":0,"covered":0,"notcovered":0,"percent":0},"regions":{"count":211,"covered":0,"notcovered":211,"percent":0}}},{"filename":"/src/hpp-proto/include/hpp_proto/binpb/sfvint.hpp","summary":{"branches":{"count":269,"covered":0,"notcovered":269,"percent":0},"functions":{"count":9,"covered":0,"percent":0},"instantiations":{"count":3131,"covered":0,"percent":0},"lines":{"count":93,"covered":0,"percent":0},"mcdc":{"count":0,"covered":0,"notcovered":0,"percent":0},"regions":{"count":295,"covered":0,"notcovered":295,"percent":0}}},{"filename":"/src/hpp-proto/include/hpp_proto/binpb/utf8.hpp","summary":{"branches":{"count":0,"covered":0,"notcovered":0,"percent":0},"functions":{"count":1,"covered":0,"percent":0},"instantiations":{"count":41,"covered":0,"percent":0},"lines":{"count":13,"covered":0,"percent":0},"mcdc":{"count":0,"covered":0,"notcovered":0,"percent":0},"regions":{"count":1,"covered":0,"notcovered":1,"percent":0}}},{"filename":"/src/hpp-proto/include/hpp_proto/binpb/util.hpp","summary":{"branches":{"count":0,"covered":0,"notcovered":0,"percent":0},"functions":{"count":3,"covered":0,"percent":0},"instantiations":{"count":292,"covered":0,"percent":0},"lines":{"count":11,"covered":0,"percent":0},"mcdc":{"count":0,"covered":0,"notcovered":0,"percent":0},"regions":{"count":4,"covered":0,"notcovered":4,"percent":0}}},{"filename":"/src/hpp-proto/include/hpp_proto/binpb/varint.hpp","summary":{"branches":{"count":51,"covered":20,"notcovered":31,"percent":39.215686274509807},"functions":{"count":17,"covered":13,"percent":76.470588235294116},"instantiations":{"count":74,"covered":28,"percent":37.837837837837839},"lines":{"count":165,"covered":94,"percent":56.969696969696969},"mcdc":{"count":0,"covered":0,"notcovered":0,"percent":0},"regions":{"count":90,"covered":50,"notcovered":40,"percent":55.555555555555557}}},{"filename":"/src/hpp-proto/include/hpp_proto/descriptor_pool.hpp","summary":{"branches":{"count":141,"covered":119,"notcovered":22,"percent":84.39716312056737},"functions":{"count":73,"covered":58,"percent":79.452054794520549},"instantiations":{"count":86,"covered":70,"percent":81.395348837209298},"lines":{"count":387,"covered":364,"percent":94.05684754521964},"mcdc":{"count":0,"covered":0,"notcovered":0,"percent":0},"regions":{"count":249,"covered":213,"notcovered":36,"percent":85.542168674698786}}},{"filename":"/src/hpp-proto/include/hpp_proto/dynamic_message/binpb.hpp","summary":{"branches":{"count":0,"covered":0,"notcovered":0,"percent":0},"functions":{"count":2,"covered":2,"percent":100},"instantiations":{"count":6,"covered":4,"percent":66.666666666666657},"lines":{"count":10,"covered":10,"percent":100},"mcdc":{"count":0,"covered":0,"notcovered":0,"percent":0},"regions":{"count":2,"covered":2,"notcovered":0,"percent":100}}},{"filename":"/src/hpp-proto/include/hpp_proto/dynamic_message/bytes_fields.hpp","summary":{"branches":{"count":10,"covered":9,"notcovered":1,"percent":90},"functions":{"count":31,"covered":17,"percent":54.838709677419352},"instantiations":{"count":33,"covered":17,"percent":51.515151515151516},"lines":{"count":75,"covered":36,"percent":48},"mcdc":{"count":0,"covered":0,"notcovered":0,"percent":0},"regions":{"count":49,"covered":33,"notcovered":16,"percent":67.346938775510196}}},{"filename":"/src/hpp-proto/include/hpp_proto/dynamic_message/enum_fields.hpp","summary":{"branches":{"count":14,"covered":12,"notcovered":2,"percent":85.714285714285708},"functions":{"count":49,"covered":26,"percent":53.061224489795919},"instantiations":{"count":51,"covered":26,"percent":50.980392156862742},"lines":{"count":104,"covered":53,"percent":50.96153846153846},"mcdc":{"count":0,"covered":0,"notcovered":0,"percent":0},"regions":{"count":74,"covered":46,"notcovered":28,"percent":62.162162162162161}}},{"filename":"/src/hpp-proto/include/hpp_proto/dynamic_message/expected_message_mref.hpp","summary":{"branches":{"count":0,"covered":0,"notcovered":0,"percent":0},"functions":{"count":9,"covered":2,"percent":22.222222222222221},"instantiations":{"count":9,"covered":2,"percent":22.222222222222221},"lines":{"count":11,"covered":2,"percent":18.181818181818183},"mcdc":{"count":0,"covered":0,"notcovered":0,"percent":0},"regions":{"count":11,"covered":3,"notcovered":8,"percent":27.27272727272727}}},{"filename":"/src/hpp-proto/include/hpp_proto/dynamic_message/factory.hpp","summary":{"branches":{"count":26,"covered":22,"notcovered":4,"percent":84.615384615384613},"functions":{"count":10,"covered":9,"percent":90},"instantiations":{"count":10,"covered":9,"percent":90},"lines":{"count":95,"covered":89,"percent":93.684210526315795},"mcdc":{"count":0,"covered":0,"notcovered":0,"percent":0},"regions":{"count":38,"covered":33,"notcovered":5,"percent":86.842105263157904}}},{"filename":"/src/hpp-proto/include/hpp_proto/dynamic_message/factory_addons.hpp","summary":{"branches":{"count":56,"covered":46,"notcovered":10,"percent":82.142857142857139},"functions":{"count":10,"covered":9,"percent":90},"instantiations":{"count":18,"covered":17,"percent":94.444444444444443},"lines":{"count":116,"covered":97,"percent":83.620689655172413},"mcdc":{"count":0,"covered":0,"notcovered":0,"percent":0},"regions":{"count":70,"covered":53,"notcovered":17,"percent":75.714285714285708}}},{"filename":"/src/hpp-proto/include/hpp_proto/dynamic_message/field_refs.hpp","summary":{"branches":{"count":6,"covered":4,"notcovered":2,"percent":66.666666666666657},"functions":{"count":23,"covered":9,"percent":39.130434782608695},"instantiations":{"count":579,"covered":9,"percent":1.5544041450777202},"lines":{"count":89,"covered":17,"percent":19.101123595505616},"mcdc":{"count":0,"covered":0,"notcovered":0,"percent":0},"regions":{"count":41,"covered":20,"notcovered":21,"percent":48.780487804878049}}},{"filename":"/src/hpp-proto/include/hpp_proto/dynamic_message/field_visit.hpp","summary":{"branches":{"count":144,"covered":141,"notcovered":3,"percent":97.916666666666657},"functions":{"count":5,"covered":3,"percent":60},"instantiations":{"count":112,"covered":22,"percent":19.642857142857142},"lines":{"count":166,"covered":149,"percent":89.759036144578303},"mcdc":{"count":0,"covered":0,"notcovered":0,"percent":0},"regions":{"count":80,"covered":75,"notcovered":5,"percent":93.75}}},{"filename":"/src/hpp-proto/include/hpp_proto/dynamic_message/json.hpp","summary":{"branches":{"count":303,"covered":101,"notcovered":202,"percent":33.333333333333329},"functions":{"count":53,"covered":29,"percent":54.716981132075468},"instantiations":{"count":2109,"covered":408,"percent":19.345661450924609},"lines":{"count":768,"covered":306,"percent":39.84375},"mcdc":{"count":0,"covered":0,"notcovered":0,"percent":0},"regions":{"count":466,"covered":153,"notcovered":313,"percent":32.832618025751067}}},{"filename":"/src/hpp-proto/include/hpp_proto/dynamic_message/message_fields.hpp","summary":{"branches":{"count":12,"covered":7,"notcovered":5,"percent":58.333333333333336},"functions":{"count":78,"covered":48,"percent":61.53846153846154},"instantiations":{"count":80,"covered":48,"percent":60},"lines":{"count":245,"covered":111,"percent":45.306122448979593},"mcdc":{"count":0,"covered":0,"notcovered":0,"percent":0},"regions":{"count":114,"covered":75,"notcovered":39,"percent":65.789473684210535}}},{"filename":"/src/hpp-proto/include/hpp_proto/dynamic_message/pb_serializer_ext.hpp","summary":{"branches":{"count":143,"covered":107,"notcovered":36,"percent":74.825174825174827},"functions":{"count":85,"covered":85,"percent":100},"instantiations":{"count":1149,"covered":615,"percent":53.52480417754569},"lines":{"count":471,"covered":420,"percent":89.171974522292999},"mcdc":{"count":0,"covered":0,"notcovered":0,"percent":0},"regions":{"count":278,"covered":251,"notcovered":27,"percent":90.287769784172667}}},{"filename":"/src/hpp-proto/include/hpp_proto/dynamic_message/repeated_bytes_fields.hpp","summary":{"branches":{"count":8,"covered":6,"notcovered":2,"percent":75},"functions":{"count":21,"covered":7,"percent":33.333333333333329},"instantiations":{"count":21,"covered":7,"percent":33.333333333333329},"lines":{"count":76,"covered":33,"percent":43.421052631578952},"mcdc":{"count":0,"covered":0,"notcovered":0,"percent":0},"regions":{"count":39,"covered":20,"notcovered":19,"percent":51.282051282051277}}},{"filename":"/src/hpp-proto/include/hpp_proto/dynamic_message/repeated_enum_fields.hpp","summary":{"branches":{"count":12,"covered":8,"notcovered":4,"percent":66.666666666666657},"functions":{"count":39,"covered":18,"percent":46.153846153846153},"instantiations":{"count":41,"covered":18,"percent":43.902439024390247},"lines":{"count":123,"covered":55,"percent":44.715447154471541},"mcdc":{"count":0,"covered":0,"notcovered":0,"percent":0},"regions":{"count":78,"covered":40,"notcovered":38,"percent":51.282051282051277}}},{"filename":"/src/hpp-proto/include/hpp_proto/dynamic_message/repeated_field_iterator.hpp","summary":{"branches":{"count":2,"covered":1,"notcovered":1,"percent":50},"functions":{"count":5,"covered":4,"percent":80},"instantiations":{"count":15,"covered":12,"percent":80},"lines":{"count":13,"covered":10,"percent":76.923076923076934},"mcdc":{"count":0,"covered":0,"notcovered":0,"percent":0},"regions":{"count":16,"covered":10,"notcovered":6,"percent":62.5}}},{"filename":"/src/hpp-proto/include/hpp_proto/dynamic_message/repeated_message_fields.hpp","summary":{"branches":{"count":14,"covered":10,"notcovered":4,"percent":71.428571428571431},"functions":{"count":31,"covered":18,"percent":58.064516129032263},"instantiations":{"count":31,"covered":18,"percent":58.064516129032263},"lines":{"count":102,"covered":64,"percent":62.745098039215684},"mcdc":{"count":0,"covered":0,"notcovered":0,"percent":0},"regions":{"count":64,"covered":41,"notcovered":23,"percent":64.0625}}},{"filename":"/src/hpp-proto/include/hpp_proto/dynamic_message/repeated_scalar_fields.hpp","summary":{"branches":{"count":10,"covered":8,"notcovered":2,"percent":80},"functions":{"count":24,"covered":19,"percent":79.166666666666657},"instantiations":{"count":351,"covered":246,"percent":70.085470085470078},"lines":{"count":80,"covered":58,"percent":72.5},"mcdc":{"count":0,"covered":0,"notcovered":0,"percent":0},"regions":{"count":63,"covered":52,"notcovered":11,"percent":82.539682539682531}}},{"filename":"/src/hpp-proto/include/hpp_proto/dynamic_message/repeated_string_fields.hpp","summary":{"branches":{"count":10,"covered":6,"notcovered":4,"percent":60},"functions":{"count":24,"covered":7,"percent":29.166666666666668},"instantiations":{"count":31,"covered":7,"percent":22.58064516129032},"lines":{"count":89,"covered":33,"percent":37.078651685393261},"mcdc":{"count":0,"covered":0,"notcovered":0,"percent":0},"regions":{"count":43,"covered":20,"notcovered":23,"percent":46.511627906976742}}},{"filename":"/src/hpp-proto/include/hpp_proto/dynamic_message/scalar_fields.hpp","summary":{"branches":{"count":10,"covered":9,"notcovered":1,"percent":90},"functions":{"count":17,"covered":15,"percent":88.235294117647058},"instantiations":{"count":247,"covered":195,"percent":78.94736842105263},"lines":{"count":45,"covered":37,"percent":82.222222222222214},"mcdc":{"count":0,"covered":0,"notcovered":0,"percent":0},"regions":{"count":46,"covered":42,"notcovered":4,"percent":91.304347826086953}}},{"filename":"/src/hpp-proto/include/hpp_proto/dynamic_message/storage.hpp","summary":{"branches":{"count":0,"covered":0,"notcovered":0,"percent":0},"functions":{"count":3,"covered":2,"percent":66.666666666666657},"instantiations":{"count":3,"covered":2,"percent":66.666666666666657},"lines":{"count":20,"covered":6,"percent":30},"mcdc":{"count":0,"covered":0,"notcovered":0,"percent":0},"regions":{"count":4,"covered":3,"notcovered":1,"percent":75}}},{"filename":"/src/hpp-proto/include/hpp_proto/dynamic_message/string_fields.hpp","summary":{"branches":{"count":10,"covered":9,"notcovered":1,"percent":90},"functions":{"count":32,"covered":17,"percent":53.125},"instantiations":{"count":34,"covered":17,"percent":50},"lines":{"count":71,"covered":31,"percent":43.661971830985912},"mcdc":{"count":0,"covered":0,"notcovered":0,"percent":0},"regions":{"count":50,"covered":33,"notcovered":17,"percent":66}}},{"filename":"/src/hpp-proto/include/hpp_proto/dynamic_message/types.hpp","summary":{"branches":{"count":0,"covered":0,"notcovered":0,"percent":0},"functions":{"count":3,"covered":0,"percent":0},"instantiations":{"count":24,"covered":0,"percent":0},"lines":{"count":3,"covered":0,"percent":0},"mcdc":{"count":0,"covered":0,"notcovered":0,"percent":0},"regions":{"count":3,"covered":0,"notcovered":3,"percent":0}}},{"filename":"/src/hpp-proto/include/hpp_proto/field_types.hpp","summary":{"branches":{"count":0,"covered":0,"notcovered":0,"percent":0},"functions":{"count":35,"covered":26,"percent":74.285714285714292},"instantiations":{"count":260,"covered":95,"percent":36.538461538461533},"lines":{"count":65,"covered":38,"percent":58.461538461538467},"mcdc":{"count":0,"covered":0,"notcovered":0,"percent":0},"regions":{"count":50,"covered":35,"notcovered":15,"percent":70}}},{"filename":"/src/hpp-proto/include/hpp_proto/file_descriptor_pb.hpp","summary":{"branches":{"count":0,"covered":0,"notcovered":0,"percent":0},"functions":{"count":2,"covered":0,"percent":0},"instantiations":{"count":2,"covered":0,"percent":0},"lines":{"count":4,"covered":0,"percent":0},"mcdc":{"count":0,"covered":0,"notcovered":0,"percent":0},"regions":{"count":2,"covered":0,"notcovered":2,"percent":0}}},{"filename":"/src/hpp-proto/include/hpp_proto/json/duration_codec.hpp","summary":{"branches":{"count":36,"covered":0,"notcovered":36,"percent":0},"functions":{"count":5,"covered":0,"percent":0},"instantiations":{"count":6,"covered":0,"percent":0},"lines":{"count":69,"covered":0,"percent":0},"mcdc":{"count":0,"covered":0,"notcovered":0,"percent":0},"regions":{"count":52,"covered":0,"notcovered":52,"percent":0}}},{"filename":"/src/hpp-proto/include/hpp_proto/json/field_mask_codec.hpp","summary":{"branches":{"count":4,"covered":0,"notcovered":4,"percent":0},"functions":{"count":3,"covered":0,"percent":0},"instantiations":{"count":3,"covered":0,"percent":0},"lines":{"count":18,"covered":0,"percent":0},"mcdc":{"count":0,"covered":0,"notcovered":0,"percent":0},"regions":{"count":7,"covered":0,"notcovered":7,"percent":0}}},{"filename":"/src/hpp-proto/include/hpp_proto/json/timestamp_codec.hpp","summary":{"branches":{"count":54,"covered":0,"notcovered":54,"percent":0},"functions":{"count":6,"covered":0,"percent":0},"instantiations":{"count":12,"covered":0,"percent":0},"lines":{"count":127,"covered":0,"percent":0},"mcdc":{"count":0,"covered":0,"notcovered":0,"percent":0},"regions":{"count":88,"covered":0,"notcovered":88,"percent":0}}},{"filename":"/src/hpp-proto/include/hpp_proto/memory_resource_utils.hpp","summary":{"branches":{"count":15,"covered":5,"notcovered":10,"percent":33.333333333333329},"functions":{"count":24,"covered":12,"percent":50},"instantiations":{"count":132,"covered":65,"percent":49.242424242424242},"lines":{"count":101,"covered":50,"percent":49.504950495049506},"mcdc":{"count":0,"covered":0,"notcovered":0,"percent":0},"regions":{"count":51,"covered":29,"notcovered":22,"percent":56.862745098039213}}},{"filename":"/src/hpp-proto/include/hpp_proto/merge.hpp","summary":{"branches":{"count":4,"covered":0,"notcovered":4,"percent":0},"functions":{"count":9,"covered":0,"percent":0},"instantiations":{"count":24,"covered":0,"percent":0},"lines":{"count":47,"covered":0,"percent":0},"mcdc":{"count":0,"covered":0,"notcovered":0,"percent":0},"regions":{"count":18,"covered":0,"notcovered":18,"percent":0}}}],"totals":{"branches":{"count":2009,"covered":818,"notcovered":1191,"percent":40.716774514683927},"functions":{"count":1289,"covered":562,"percent":43.599689681923969},"instantiations":{"count":15568,"covered":2648,"percent":17.009249743062693},"lines":{"count":6860,"covered":3036,"percent":44.25655976676385},"mcdc":{"count":0,"covered":0,"notcovered":0,"percent":0},"regions":{"count":4108,"covered":1828,"notcovered":2280,"percent":44.498539435248297}}}],"type":"llvm.coverage.json.export","version":"3.0.1"}